[{"name": "acoustic_iso.IsotropicAcousticForward.track_gflopss", "idx": 0, "pretty_name": "acoustic_iso.IsotropicAcousticForward.track_gflopss((492, 492, 492), 12, {'rec': 109.070557, 'u': 144.055939})", "last_rev": 257, "last_value": 61.38517432233344, "last_err": 8.007698984614077, "prev_value": null, "change_rev": null}, {"name": "acoustic_iso.IsotropicAcousticForward.track_gpointss", "idx": 0, "pretty_name": "acoustic_iso.IsotropicAcousticForward.track_gpointss((492, 492, 492), 12, {'rec': 109.070557, 'u': 144.055939})", "last_rev": 257, "last_value": 1.0431823368399764, "last_err": 0.12317796205951889, "prev_value": null, "change_rev": null}, {"name": "acoustic_iso.IsotropicAcousticForward.track_runtime", "idx": 0, "pretty_name": "acoustic_iso.IsotropicAcousticForward.track_runtime((492, 492, 492), 12, {'rec': 109.070557, 'u': 144.055939})", "last_rev": 257, "last_value": 5.403796315193176, "last_err": 1.7040546834468842, "prev_value": null, "change_rev": null}, {"name": "acoustic_iso_adj.IsotropicAcousticAdjoint.track_gflopss", "idx": 0, "pretty_name": "acoustic_iso_adj.IsotropicAcousticAdjoint.track_gflopss((492, 492, 492), 12, {'srca': 646.188904, 'v': 347421.625})", "last_rev": 257, "last_value": 60.37361962292372, "last_err": 0.0, "prev_value": 61.50485629450164, "change_rev": [250, 257]}, {"name": "acoustic_iso_adj.IsotropicAcousticAdjoint.track_gpointss", "idx": 0, "pretty_name": "acoustic_iso_adj.IsotropicAcousticAdjoint.track_gpointss((492, 492, 492), 12, {'srca': 646.188904, 'v': 347421.625})", "last_rev": 257, "last_value": 0.9848107179596446, "last_err": 0.0, "prev_value": 1.0032633799944373, "change_rev": [250, 257]}, {"name": "acoustic_iso_adj.IsotropicAcousticAdjoint.track_runtime", "idx": 0, "pretty_name": "acoustic_iso_adj.IsotropicAcousticAdjoint.track_runtime((492, 492, 492), 12, {'srca': 646.188904, 'v': 347421.625})", "last_rev": 257, "last_value": 5.7240893840789795, "last_err": 0.0, "prev_value": 5.618808269500732, "change_rev": [250, 257]}, {"name": "acoustic_iso_jac.IsotropicAcousticJacobian.track_gflopss", "idx": 0, "pretty_name": "acoustic_iso_jac.IsotropicAcousticJacobian.track_gflopss((152, 152, 152), 12, {'rec': 4.95217, 'u': 144.055573, 'U': 4.879143})", "last_rev": 257, "last_value": 54.60773307409336, "last_err": 0.0, "prev_value": 56.36376058448459, "change_rev": [250, 257]}, {"name": "acoustic_iso_jac.IsotropicAcousticJacobian.track_gpointss", "idx": 0, "pretty_name": "acoustic_iso_jac.IsotropicAcousticJacobian.track_gpointss((152, 152, 152), 12, {'rec': 4.95217, 'u': 144.055573, 'U': 4.879143})", "last_rev": 257, "last_value": 0.4245595582725686, "last_err": 0.0, "prev_value": 0.4382121715959346, "change_rev": [250, 257]}, {"name": "acoustic_iso_jac.IsotropicAcousticJacobian.track_runtime", "idx": 0, "pretty_name": "acoustic_iso_jac.IsotropicAcousticJacobian.track_runtime((152, 152, 152), 12, {'rec': 4.95217, 'u': 144.055573, 'U': 4.879143})", "last_rev": 257, "last_value": 0.5010883808135986, "last_err": 0.21910762786865234, "prev_value": null, "change_rev": null}, {"name": "acoustic_iso_jacadj.IsotropicAcousticJacobianAdjoint.track_gflopss", "idx": 0, "pretty_name": "acoustic_iso_jacadj.IsotropicAcousticJacobianAdjoint.track_gflopss((151, 151, 151), 12, {'grad': 2468.533936})", "last_rev": 257, "last_value": 29.283375785490506, "last_err": 0.0, "prev_value": 29.318581656104243, "change_rev": [250, 257]}, {"name": "acoustic_iso_jacadj.IsotropicAcousticJacobianAdjoint.track_gpointss", "idx": 0, "pretty_name": "acoustic_iso_jacadj.IsotropicAcousticJacobianAdjoint.track_gpointss((151, 151, 151), 12, {'grad': 2468.533936})", "last_rev": 257, "last_value": 0.4258121669494879, "last_err": 0.0, "prev_value": 0.42632409863950865, "change_rev": [250, 257]}, {"name": "acoustic_iso_jacadj.IsotropicAcousticJacobianAdjoint.track_runtime", "idx": 0, "pretty_name": "acoustic_iso_jacadj.IsotropicAcousticJacobianAdjoint.track_runtime((151, 151, 151), 12, {'grad': 2468.533936})", "last_rev": 257, "last_value": 0.5047144889831543, "last_err": 1.102885913848877, "prev_value": null, "change_rev": null}, {"name": "acoustic_iso_ssa.IsotropicSSAForward.track_gflopss", "idx": 0, "pretty_name": "acoustic_iso_ssa.IsotropicSSAForward.track_gflopss((152, 152, 152), 12, {'rec': 247.9561, 'u': 7438246.5})", "last_rev": 257, "last_value": 74.70117514873817, "last_err": 6.604647920198168, "prev_value": null, "change_rev": null}, {"name": "acoustic_iso_ssa.IsotropicSSAForward.track_gpointss", "idx": 0, "pretty_name": "acoustic_iso_ssa.IsotropicSSAForward.track_gpointss((152, 152, 152), 12, {'rec': 247.9561, 'u': 7438246.5})", "last_rev": 257, "last_value": 0.4945588350822829, "last_err": 0.043726045474359626, "prev_value": null, "change_rev": null}, {"name": "acoustic_iso_ssa.IsotropicSSAForward.track_runtime", "idx": 0, "pretty_name": "acoustic_iso_ssa.IsotropicSSAForward.track_runtime((152, 152, 152), 12, {'rec': 247.9561, 'u': 7438246.5})", "last_rev": 257, "last_value": 0.9363021850585938, "last_err": 0.13181686401367188, "prev_value": null, "change_rev": null}, {"name": "acoustic_iso_ssa_adj.IsotropicSSAAdjoint.track_gflopss", "idx": 0, "pretty_name": "acoustic_iso_ssa_adj.IsotropicSSAAdjoint.track_gflopss((152, 152, 152), 12, {'srca': 390.499268, 'v': 157214277632.0})", "last_rev": 257, "last_value": 72.39789808151234, "last_err": 0.0, "prev_value": 71.38118074728861, "change_rev": [250, 257]}, {"name": "acoustic_iso_ssa_adj.IsotropicSSAAdjoint.track_gpointss", "idx": 0, "pretty_name": "acoustic_iso_ssa_adj.IsotropicSSAAdjoint.track_gpointss((152, 152, 152), 12, {'srca': 390.499268, 'v': 157214277632.0})", "last_rev": 257, "last_value": 0.47861943244801425, "last_err": 0.0, "prev_value": 0.4718979572897391, "change_rev": [250, 257]}, {"name": "acoustic_iso_ssa_adj.IsotropicSSAAdjoint.track_runtime", "idx": 0, "pretty_name": "acoustic_iso_ssa_adj.IsotropicSSAAdjoint.track_runtime((152, 152, 152), 12, {'srca': 390.499268, 'v': 157214277632.0})", "last_rev": 257, "last_value": 0.9674675464630127, "last_err": 0.0, "prev_value": 0.9812476634979248, "change_rev": [250, 257]}, {"name": "acoustic_iso_ssa_jac.IsotropicSSAJacobian.track_gflopss", "idx": 0, "pretty_name": "acoustic_iso_ssa_jac.IsotropicSSAJacobian.track_gflopss((152, 152, 152), 12, {'rec': 0.070716, 'u0': 7438246.0, 'du': 18011874.0})", "last_rev": 257, "last_value": 79.71803447604498, "last_err": 0.0, "prev_value": 80.87093566569155, "change_rev": [250, 257]}, {"name": "acoustic_iso_ssa_jac.IsotropicSSAJacobian.track_gpointss", "idx": 0, "pretty_name": "acoustic_iso_ssa_jac.IsotropicSSAJacobian.track_gpointss((152, 152, 152), 12, {'rec': 0.070716, 'u0': 7438246.0, 'du': 18011874.0})", "last_rev": 257, "last_value": 0.2503156127831786, "last_err": 0.0, "prev_value": 0.2539357367571528, "change_rev": [250, 257]}, {"name": "acoustic_iso_ssa_jac.IsotropicSSAJacobian.track_runtime", "idx": 0, "pretty_name": "acoustic_iso_ssa_jac.IsotropicSSAJacobian.track_runtime((152, 152, 152), 12, {'rec': 0.070716, 'u0': 7438246.0, 'du': 18011874.0})", "last_rev": 257, "last_value": 1.8498597145080566, "last_err": 0.0, "prev_value": 1.8234879970550537, "change_rev": [250, 257]}, {"name": "acoustic_iso_ssa_jacadj.IsotropicSSAJacobianAdjoint.track_gflopss", "idx": 0, "pretty_name": "acoustic_iso_ssa_jacadj.IsotropicSSAJacobianAdjoint.track_gflopss((152, 152, 152), 12, {'dm': 16766.755859, 'u': 7628539.0, 'du': 3355461376.0})", "last_rev": 257, "last_value": 51.8784317972588, "last_err": 0.0, "prev_value": 53.666814147331976, "change_rev": [250, 257]}, {"name": "acoustic_iso_ssa_jacadj.IsotropicSSAJacobianAdjoint.track_gpointss", "idx": 0, "pretty_name": "acoustic_iso_ssa_jacadj.IsotropicSSAJacobianAdjoint.track_gpointss((152, 152, 152), 12, {'dm': 16766.755859, 'u': 7628539.0, 'du': 3355461376.0})", "last_rev": 257, "last_value": 0.3083157109227977, "last_err": 0.0, "prev_value": 0.3189441427501015, "change_rev": [250, 257]}, {"name": "acoustic_iso_ssa_jacadj.IsotropicSSAJacobianAdjoint.track_runtime", "idx": 0, "pretty_name": "acoustic_iso_ssa_jacadj.IsotropicSSAJacobianAdjoint.track_runtime((152, 152, 152), 12, {'dm': 16766.755859, 'u': 7628539.0, 'du': 3355461376.0})", "last_rev": 257, "last_value": 1.5018656253814697, "last_err": 0.0, "prev_value": 1.4518177509307861, "change_rev": [250, 257]}, {"name": "acoustic_tti.TTIAcousticForward.track_gflopss", "idx": 0, "pretty_name": "acoustic_tti.TTIAcousticForward.track_gflopss((350, 350, 350), 12, {'rec': 17.805016, 'u': 29.331156, 'v': 29.331171})", "last_rev": 257, "last_value": 68.31639322624261, "last_err": 4.919684004966714, "prev_value": null, "change_rev": null}, {"name": "acoustic_tti.TTIAcousticForward.track_gpointss", "idx": 0, "pretty_name": "acoustic_tti.TTIAcousticForward.track_gpointss((350, 350, 350), 12, {'rec': 17.805016, 'u': 29.331156, 'v': 29.331171})", "last_rev": 257, "last_value": 0.27849493079557863, "last_err": 0.01960878849863118, "prev_value": null, "change_rev": null}, {"name": "acoustic_tti.TTIAcousticForward.track_runtime", "idx": 0, "pretty_name": "acoustic_tti.TTIAcousticForward.track_runtime((350, 350, 350), 12, {'rec': 17.805016, 'u': 29.331156, 'v': 29.331171})", "last_rev": 257, "last_value": 5.640432119369507, "last_err": 0.06353004773457845, "prev_value": 17.750516414642334, "change_rev": [null, 245]}, {"name": "acoustic_tti_adj.TTIAcousticAdjoint.track_gflopss", "idx": 0, "pretty_name": "acoustic_tti_adj.TTIAcousticAdjoint.track_gflopss((350, 350, 350), 12, {'srca': 1588.117065, 'p': 568135.6875, 'r': 620591.5})", "last_rev": 257, "last_value": 61.48002109409372, "last_err": 5.160934404760992, "prev_value": null, "change_rev": null}, {"name": "acoustic_tti_adj.TTIAcousticAdjoint.track_gpointss", "idx": 0, "pretty_name": "acoustic_tti_adj.TTIAcousticAdjoint.track_gpointss((350, 350, 350), 12, {'srca': 1588.117065, 'p': 568135.6875, 'r': 620591.5})", "last_rev": 257, "last_value": 0.10279670838622348, "last_err": 0.0083111132480647, "prev_value": null, "change_rev": null}, {"name": "acoustic_tti_adj.TTIAcousticAdjoint.track_runtime", "idx": 0, "pretty_name": "acoustic_tti_adj.TTIAcousticAdjoint.track_runtime((350, 350, 350), 12, {'srca': 1588.117065, 'p': 568135.6875, 'r': 620591.5})", "last_rev": 257, "last_value": 31.04320216178894, "last_err": 2.7632024765014647, "prev_value": null, "change_rev": null}, {"name": "elastic.Elastic.track_gflopss", "idx": 0, "pretty_name": "elastic.Elastic.track_gflopss((100, 100, 100), 12, {'rec1': 2.814472, 'rec2': 0.119794})", "last_rev": 257, "last_value": 52.544471843692506, "last_err": 4.13725952049997, "prev_value": null, "change_rev": null}, {"name": "elastic.Elastic.track_gpointss", "idx": 0, "pretty_name": "elastic.Elastic.track_gpointss((100, 100, 100), 12, {'rec1': 2.814472, 'rec2': 0.119794})", "last_rev": 257, "last_value": 0.14206087171734116, "last_err": 0.011185623784581787, "prev_value": null, "change_rev": null}, {"name": "elastic.Elastic.track_runtime", "idx": 0, "pretty_name": "elastic.Elastic.track_runtime((100, 100, 100), 12, {'rec1': 2.814472, 'rec2': 0.119794})", "last_rev": 257, "last_value": 0.48793959617614746, "last_err": 0.0, "prev_value": 0.48787927627563477, "change_rev": [250, 257]}, {"name": "viscoelastic.Viscoelastic.track_gflopss", "idx": 0, "pretty_name": "viscoelastic.Viscoelastic.track_gflopss((100, 100, 100), 12, {'rec1': 3.314084, 'rec2': 0.049992})", "last_rev": 257, "last_value": 33.57189472597912, "last_err": 3.099040385664733, "prev_value": null, "change_rev": null}, {"name": "viscoelastic.Viscoelastic.track_gpointss", "idx": 0, "pretty_name": "viscoelastic.Viscoelastic.track_gpointss((100, 100, 100), 12, {'rec1': 3.314084, 'rec2': 0.049992})", "last_rev": 257, "last_value": 0.0741309360506422, "last_err": 0.006843068183169685, "prev_value": null, "change_rev": null}, {"name": "viscoelastic.Viscoelastic.track_runtime", "idx": 0, "pretty_name": "viscoelastic.Viscoelastic.track_runtime((100, 100, 100), 12, {'rec1': 3.314084, 'rec2': 0.049992})", "last_rev": 257, "last_value": 0.39685535430908203, "last_err": 0.005799929300944011, "prev_value": 1.8190233707427979, "change_rev": [null, 245]}]