[{"name": "acoustic_iso.IsotropicAcousticForward.track_gflopss", "idx": 0, "pretty_name": "acoustic_iso.IsotropicAcousticForward.track_gflopss((492, 492, 492), 12, {'rec': 109.070557, 'u': 144.055939})", "last_rev": 241, "last_value": 54.42449222990297, "last_err": 0.0, "prev_value": 53.55358457400401, "change_rev": [235, 241]}, {"name": "acoustic_iso.IsotropicAcousticForward.track_gpointss", "idx": 0, "pretty_name": "acoustic_iso.IsotropicAcousticForward.track_gpointss((492, 492, 492), 12, {'rec': 109.070557, 'u': 144.055939})", "last_rev": 241, "last_value": 0.9506945900039567, "last_err": 0.0, "prev_value": 0.9354814540989194, "change_rev": [235, 241]}, {"name": "acoustic_iso.IsotropicAcousticForward.track_runtime", "idx": 0, "pretty_name": "acoustic_iso.IsotropicAcousticForward.track_runtime((492, 492, 492), 12, {'rec': 109.070557, 'u': 144.055939})", "last_rev": 241, "last_value": 5.929501056671143, "last_err": 0.0, "prev_value": 6.025928735733032, "change_rev": [235, 241]}, {"name": "acoustic_iso_adj.IsotropicAcousticAdjoint.track_gflopss", "idx": 0, "pretty_name": "acoustic_iso_adj.IsotropicAcousticAdjoint.track_gflopss((492, 492, 492), 12, {'srca': 646.188904, 'v': 347421.625})", "last_rev": 241, "last_value": 51.530525109708535, "last_err": 0.0, "prev_value": null, "change_rev": null}, {"name": "acoustic_iso_adj.IsotropicAcousticAdjoint.track_gpointss", "idx": 0, "pretty_name": "acoustic_iso_adj.IsotropicAcousticAdjoint.track_gpointss((492, 492, 492), 12, {'srca': 646.188904, 'v': 347421.625})", "last_rev": 241, "last_value": 0.89923582666577, "last_err": 0.0, "prev_value": null, "change_rev": null}, {"name": "acoustic_iso_adj.IsotropicAcousticAdjoint.track_runtime", "idx": 0, "pretty_name": "acoustic_iso_adj.IsotropicAcousticAdjoint.track_runtime((492, 492, 492), 12, {'srca': 646.188904, 'v': 347421.625})", "last_rev": 241, "last_value": 6.268816709518433, "last_err": 0.0, "prev_value": null, "change_rev": null}, {"name": "acoustic_iso_jac.IsotropicAcousticJacobian.track_gflopss", "idx": 0, "pretty_name": "acoustic_iso_jac.IsotropicAcousticJacobian.track_gflopss((152, 152, 152), 12, {'rec': 4.95217, 'u': 144.055573, 'U': 4.879143})", "last_rev": 241, "last_value": 37.79276902091737, "last_err": 0.0, "prev_value": null, "change_rev": null}, {"name": "acoustic_iso_jac.IsotropicAcousticJacobian.track_gpointss", "idx": 0, "pretty_name": "acoustic_iso_jac.IsotropicAcousticJacobian.track_gpointss((152, 152, 152), 12, {'rec': 4.95217, 'u': 144.055573, 'U': 4.879143})", "last_rev": 241, "last_value": 0.3107393765168261, "last_err": 0.0, "prev_value": null, "change_rev": null}, {"name": "acoustic_iso_jac.IsotropicAcousticJacobian.track_runtime", "idx": 0, "pretty_name": "acoustic_iso_jac.IsotropicAcousticJacobian.track_runtime((152, 152, 152), 12, {'rec': 4.95217, 'u': 144.055573, 'U': 4.879143})", "last_rev": 241, "last_value": 0.6877622604370117, "last_err": 0.0, "prev_value": null, "change_rev": null}, {"name": "acoustic_iso_jacadj.IsotropicAcousticJacobianAdjoint.track_gflopss", "idx": 0, "pretty_name": "acoustic_iso_jacadj.IsotropicAcousticJacobianAdjoint.track_gflopss((151, 151, 151), 12, {'grad': 2468.533936})", "last_rev": 241, "last_value": 17.772333098073968, "last_err": 0.0, "prev_value": null, "change_rev": null}, {"name": "acoustic_iso_jacadj.IsotropicAcousticJacobianAdjoint.track_gpointss", "idx": 0, "pretty_name": "acoustic_iso_jacadj.IsotropicAcousticJacobianAdjoint.track_gpointss((151, 151, 151), 12, {'grad': 2468.533936})", "last_rev": 241, "last_value": 0.2743887160470825, "last_err": 0.0, "prev_value": null, "change_rev": null}, {"name": "acoustic_iso_jacadj.IsotropicAcousticJacobianAdjoint.track_runtime", "idx": 0, "pretty_name": "acoustic_iso_jacadj.IsotropicAcousticJacobianAdjoint.track_runtime((151, 151, 151), 12, {'grad': 2468.533936})", "last_rev": 241, "last_value": 0.7653698921203613, "last_err": 0.0, "prev_value": null, "change_rev": null}, {"name": "acoustic_iso_ssa.IsotropicSSAForward.track_gflopss", "idx": 0, "pretty_name": "acoustic_iso_ssa.IsotropicSSAForward.track_gflopss((152, 152, 152), 12, {'rec': 247.9561, 'u': 7438246.5})", "last_rev": 241, "last_value": 42.893221495719075, "last_err": 1.3759133216682002, "prev_value": null, "change_rev": null}, {"name": "acoustic_iso_ssa.IsotropicSSAForward.track_gpointss", "idx": 0, "pretty_name": "acoustic_iso_ssa.IsotropicSSAForward.track_gpointss((152, 152, 152), 12, {'rec': 247.9561, 'u': 7438246.5})", "last_rev": 241, "last_value": 0.28397440352994896, "last_err": 0.00910922871271476, "prev_value": null, "change_rev": null}, {"name": "acoustic_iso_ssa.IsotropicSSAForward.track_runtime", "idx": 0, "pretty_name": "acoustic_iso_ssa.IsotropicSSAForward.track_runtime((152, 152, 152), 12, {'rec': 247.9561, 'u': 7438246.5})", "last_rev": 241, "last_value": 1.6306250095367432, "last_err": 0.053393661975860596, "prev_value": null, "change_rev": null}, {"name": "acoustic_iso_ssa_adj.IsotropicSSAAdjoint.track_gflopss", "idx": 0, "pretty_name": "acoustic_iso_ssa_adj.IsotropicSSAAdjoint.track_gflopss((152, 152, 152), 12, {'srca': 390.499268, 'v': 157214277632.0})", "last_rev": 241, "last_value": 40.217020748870354, "last_err": 0.0, "prev_value": null, "change_rev": null}, {"name": "acoustic_iso_ssa_adj.IsotropicSSAAdjoint.track_gpointss", "idx": 0, "pretty_name": "acoustic_iso_ssa_adj.IsotropicSSAAdjoint.track_gpointss((152, 152, 152), 12, {'srca': 390.499268, 'v': 157214277632.0})", "last_rev": 241, "last_value": 0.26587301780367173, "last_err": 0.0, "prev_value": null, "change_rev": null}, {"name": "acoustic_iso_ssa_adj.IsotropicSSAAdjoint.track_runtime", "idx": 0, "pretty_name": "acoustic_iso_ssa_adj.IsotropicSSAAdjoint.track_runtime((152, 152, 152), 12, {'srca': 390.499268, 'v': 157214277632.0})", "last_rev": 241, "last_value": 1.7416162490844727, "last_err": 0.0, "prev_value": null, "change_rev": null}, {"name": "acoustic_iso_ssa_jac.IsotropicSSAJacobian.track_gflopss", "idx": 0, "pretty_name": "acoustic_iso_ssa_jac.IsotropicSSAJacobian.track_gflopss((152, 152, 152), 12, {'rec': 0.070716, 'u0': 7438246.0, 'du': 18011874.0})", "last_rev": 241, "last_value": 43.95534957763082, "last_err": 0.0, "prev_value": null, "change_rev": null}, {"name": "acoustic_iso_ssa_jac.IsotropicSSAJacobian.track_gpointss", "idx": 0, "pretty_name": "acoustic_iso_ssa_jac.IsotropicSSAJacobian.track_gpointss((152, 152, 152), 12, {'rec': 0.070716, 'u0': 7438246.0, 'du': 18011874.0})", "last_rev": 241, "last_value": 0.13802034052821222, "last_err": 0.0, "prev_value": null, "change_rev": null}, {"name": "acoustic_iso_ssa_jac.IsotropicSSAJacobian.track_runtime", "idx": 0, "pretty_name": "acoustic_iso_ssa_jac.IsotropicSSAJacobian.track_runtime((152, 152, 152), 12, {'rec': 0.070716, 'u0': 7438246.0, 'du': 18011874.0})", "last_rev": 241, "last_value": 3.354931354522705, "last_err": 0.0, "prev_value": null, "change_rev": null}, {"name": "acoustic_tti.TTIAcousticForward.track_gflopss", "idx": 0, "pretty_name": "acoustic_tti.TTIAcousticForward.track_gflopss((350, 350, 350), 12, {'rec': 17.805016, 'u': 29.331156, 'v': 29.331171})", "last_rev": 241, "last_value": 49.10154983595156, "last_err": 0.9049312530659757, "prev_value": null, "change_rev": null}, {"name": "acoustic_tti.TTIAcousticForward.track_gpointss", "idx": 0, "pretty_name": "acoustic_tti.TTIAcousticForward.track_gpointss((350, 350, 350), 12, {'rec': 17.805016, 'u': 29.331156, 'v': 29.331171})", "last_rev": 241, "last_value": 0.19993681645062095, "last_err": 0.0035802072101825053, "prev_value": null, "change_rev": null}, {"name": "acoustic_tti.TTIAcousticForward.track_runtime", "idx": 0, "pretty_name": "acoustic_tti.TTIAcousticForward.track_runtime((350, 350, 350), 12, {'rec': 17.805016, 'u': 29.331156, 'v': 29.331171})", "last_rev": 241, "last_value": 7.854703068733215, "last_err": 0.14056548476219177, "prev_value": null, "change_rev": null}, {"name": "acoustic_tti_adj.TTIAcousticAdjoint.track_gflopss", "idx": 0, "pretty_name": "acoustic_tti_adj.TTIAcousticAdjoint.track_gflopss((350, 350, 350), 12, {'srca': 1588.117065, 'p': 568135.6875, 'r': 620591.5})", "last_rev": 241, "last_value": 58.62958693774237, "last_err": 0.0, "prev_value": null, "change_rev": null}, {"name": "acoustic_tti_adj.TTIAcousticAdjoint.track_gpointss", "idx": 0, "pretty_name": "acoustic_tti_adj.TTIAcousticAdjoint.track_gpointss((350, 350, 350), 12, {'srca': 1588.117065, 'p': 568135.6875, 'r': 620591.5})", "last_rev": 241, "last_value": 0.09381302345405652, "last_err": 0.0, "prev_value": null, "change_rev": null}, {"name": "acoustic_tti_adj.TTIAcousticAdjoint.track_runtime", "idx": 0, "pretty_name": "acoustic_tti_adj.TTIAcousticAdjoint.track_runtime((350, 350, 350), 12, {'srca': 1588.117065, 'p': 568135.6875, 'r': 620591.5})", "last_rev": 241, "last_value": 34.01594877243042, "last_err": 0.0, "prev_value": null, "change_rev": null}, {"name": "elastic.Elastic.track_gflopss", "idx": 0, "pretty_name": "elastic.Elastic.track_gflopss((100, 100, 100), 12, {'rec1': 2.814472, 'rec2': 0.119794})", "last_rev": 241, "last_value": 28.58523201050305, "last_err": 1.2326232198110416, "prev_value": null, "change_rev": null}, {"name": "elastic.Elastic.track_gpointss", "idx": 0, "pretty_name": "elastic.Elastic.track_gpointss((100, 100, 100), 12, {'rec1': 2.814472, 'rec2': 0.119794})", "last_rev": 241, "last_value": 0.07728392417254787, "last_err": 0.0033325585539482876, "prev_value": null, "change_rev": null}, {"name": "elastic.Elastic.track_runtime", "idx": 0, "pretty_name": "elastic.Elastic.track_runtime((100, 100, 100), 12, {'rec1': 2.814472, 'rec2': 0.119794})", "last_rev": 241, "last_value": 0.8050154447555542, "last_err": 0.04127183556556702, "prev_value": null, "change_rev": null}, {"name": "viscoelastic.Viscoelastic.track_gflopss", "idx": 0, "pretty_name": "viscoelastic.Viscoelastic.track_gflopss((100, 100, 100), 12, {'rec1': 3.314084, 'rec2': 0.049992})", "last_rev": 241, "last_value": 26.81370754489649, "last_err": 0.6439749295937593, "prev_value": null, "change_rev": null}, {"name": "viscoelastic.Viscoelastic.track_gpointss", "idx": 0, "pretty_name": "viscoelastic.Viscoelastic.track_gpointss((100, 100, 100), 12, {'rec1': 3.314084, 'rec2': 0.049992})", "last_rev": 241, "last_value": 0.05920801478485428, "last_err": 0.0014219770648509177, "prev_value": null, "change_rev": null}, {"name": "viscoelastic.Viscoelastic.track_runtime", "idx": 0, "pretty_name": "viscoelastic.Viscoelastic.track_runtime((100, 100, 100), 12, {'rec1': 3.314084, 'rec2': 0.049992})", "last_rev": 241, "last_value": 0.4669973850250244, "last_err": 0.011398166418075562, "prev_value": null, "change_rev": null}]